[
  {
    "day": 1,
    "month": "4",
    "firstDish": {
      "label": "Paella de pollo | Arroz blanco salteado",
      "quality": -2
    },
    "secondDish": {
      "label": "Tortilla francesa + ensalada de colores ",
      "quality": -2
    },
    "dessertDish": {
      "label": "Pan, yogur",
      "quality": -2
    },
    "nap": {
      "label": "",
      "quality": -2
    },
    "snack": {
      "label": "",
      "quality": -2
    },
    "deposiciones": {
      "label": "",
      "quality": -2
    },
    "teacherComments": "Hoy todav\u00eda no han comentado nada"
  },
  {
    "day": 2,
    "month": "4",
    "firstDish": {
      "label": "Lentejas con chorizo | Pure de lentejas",
      "quality": -2
    },
    "secondDish": {
      "label": "Chuleta de pavo al ajillo + tomate ali\u00f1ado ",
      "quality": -2
    },
    "dessertDish": {
      "label": "Pan integral, fruta",
      "quality": -2
    },
    "nap": {
      "label": "",
      "quality": -2
    },
    "snack": {
      "label": "",
      "quality": -2
    },
    "deposiciones": {
      "label": "",
      "quality": -2
    },
    "teacherComments": "Hoy todav\u00eda no han comentado nada"
  },
  {
    "day": 3,
    "month": "4",
    "firstDish": {
      "label": "Crema de acelgas y verduras | Menestra de verdura salteada",
      "quality": -2
    },
    "secondDish": {
      "label": " filete de ternera en salsa + zanahoria baby + ensalada con maiz ",
      "quality": -2
    },
    "dessertDish": {
      "label": "Pan, yogur",
      "quality": -2
    },
    "nap": {
      "label": "",
      "quality": -2
    },
    "snack": {
      "label": "",
      "quality": -2
    },
    "deposiciones": {
      "label": "",
      "quality": -2
    },
    "teacherComments": "Hoy todav\u00eda no han comentado nada"
  },
  {
    "day": 4,
    "month": "4",
    "firstDish": {
      "label": "Judias pintas con verduras | Crema de alubias pintas",
      "quality": -2
    },
    "secondDish": {
      "label": "Dorada al horno + patatas con hierbas provenzales + ensalada con aceitunas ",
      "quality": -2
    },
    "dessertDish": {
      "label": "Pan, fruta",
      "quality": -2
    },
    "nap": {
      "label": "",
      "quality": -2
    },
    "snack": {
      "label": "",
      "quality": -2
    },
    "deposiciones": {
      "label": "",
      "quality": -2
    },
    "teacherComments": "Hoy todav\u00eda no han comentado nada"
  },
  {
    "day": 7,
    "month": "4",
    "firstDish": {
      "label": "Patatas con magro | Patatas con verduras",
      "quality": -2
    },
    "secondDish": {
      "label": "Revuelto de huevos con pavo + ensalada verde ",
      "quality": -2
    },
    "dessertDish": {
      "label": "Pan, fruta",
      "quality": -2
    },
    "nap": {
      "label": "",
      "quality": -2
    },
    "snack": {
      "label": "",
      "quality": -2
    },
    "deposiciones": {
      "label": "",
      "quality": -2
    },
    "teacherComments": "Hoy todav\u00eda no han comentado nada"
  },
  {
    "day": 8,
    "month": "4",
    "firstDish": {
      "label": "Sopa de cocido",
      "quality": -2
    },
    "secondDish": {
      "label": "Cocido completo ",
      "quality": -2
    },
    "dessertDish": {
      "label": "Pan, yogur",
      "quality": -2
    },
    "nap": {
      "label": "",
      "quality": -2
    },
    "snack": {
      "label": "",
      "quality": -2
    },
    "deposiciones": {
      "label": "",
      "quality": -2
    },
    "teacherComments": "Hoy todav\u00eda no han comentado nada"
  },
  {
    "day": 9,
    "month": "4",
    "firstDish": {
      "label": " brocoli con queso | Pur\u00e9 de brocoli",
      "quality": -2
    },
    "secondDish": {
      "label": "Escalope de pollo + arroz salteado + ensalada con remolacha ",
      "quality": -2
    },
    "dessertDish": {
      "label": "Pan integral, fruta",
      "quality": -2
    },
    "nap": {
      "label": "",
      "quality": -2
    },
    "snack": {
      "label": "",
      "quality": -2
    },
    "deposiciones": {
      "label": "",
      "quality": -2
    },
    "teacherComments": "Hoy todav\u00eda no han comentado nada"
  },
  {
    "day": 10,
    "month": "4",
    "firstDish": {
      "label": "Alubias blancas estofadas | Crema de alubias",
      "quality": -2
    },
    "secondDish": {
      "label": "Salmon al eneldo + ensalada del tiempo ",
      "quality": -2
    },
    "dessertDish": {
      "label": "Pan, actimel",
      "quality": -2
    },
    "nap": {
      "label": "",
      "quality": -2
    },
    "snack": {
      "label": "",
      "quality": -2
    },
    "deposiciones": {
      "label": "",
      "quality": -2
    },
    "teacherComments": "Hoy todav\u00eda no han comentado nada"
  },
  {
    "day": 22,
    "month": "4",
    "firstDish": {
      "label": "Arroz tres delicias | Arroz blanco al ajillo",
      "quality": -2
    },
    "secondDish": {
      "label": "Alb\u00f3ndigas  a la jardinera + ensalada de colores ",
      "quality": -2
    },
    "dessertDish": {
      "label": "Pan, yogur",
      "quality": -2
    },
    "nap": {
      "label": "",
      "quality": -2
    },
    "snack": {
      "label": "",
      "quality": -2
    },
    "deposiciones": {
      "label": "",
      "quality": -2
    },
    "teacherComments": "Hoy todav\u00eda no han comentado nada"
  },
  {
    "day": 23,
    "month": "4",
    "firstDish": {
      "label": "Sopa de estrellas | Ensalada completa",
      "quality": -2
    },
    "secondDish": {
      "label": "Lubina a la espalda + boniato frito + lechuga y zanahoria ",
      "quality": -2
    },
    "dessertDish": {
      "label": "Pan integral, fruta",
      "quality": -2
    },
    "nap": {
      "label": "",
      "quality": -2
    },
    "snack": {
      "label": "",
      "quality": -2
    },
    "deposiciones": {
      "label": "",
      "quality": -2
    },
    "teacherComments": "Hoy todav\u00eda no han comentado nada"
  },
  {
    "day": 24,
    "month": "4",
    "firstDish": {
      "label": "Crema de calabacin | Alcachofas salteadas",
      "quality": -2
    },
    "secondDish": {
      "label": "Pollo asado al limon + ensalada del tiempo ",
      "quality": -2
    },
    "dessertDish": {
      "label": "Pan, yogur",
      "quality": -2
    },
    "nap": {
      "label": "",
      "quality": -2
    },
    "snack": {
      "label": "",
      "quality": -2
    },
    "deposiciones": {
      "label": "",
      "quality": -2
    },
    "teacherComments": "Hoy todav\u00eda no han comentado nada"
  },
  {
    "day": 25,
    "month": "4",
    "firstDish": {
      "label": "Lentejas con verduras | Crema de lentejas",
      "quality": -2
    },
    "secondDish": {
      "label": "Bacalao con tomate + ensalada verde ",
      "quality": -2
    },
    "dessertDish": {
      "label": "Pan, fruta",
      "quality": -2
    },
    "nap": {
      "label": "",
      "quality": -2
    },
    "snack": {
      "label": "",
      "quality": -2
    },
    "deposiciones": {
      "label": "",
      "quality": -2
    },
    "teacherComments": "Hoy todav\u00eda no han comentado nada"
  },
  {
    "day": 28,
    "month": "4",
    "firstDish": {
      "label": "Guisantes salteados con jamon | Pure de guisantes",
      "quality": -2
    },
    "secondDish": {
      "label": "Cinta de lomo a la plancha + patatas fritas + ensalada con aceitunas ",
      "quality": -2
    },
    "dessertDish": {
      "label": "Pan, fruta",
      "quality": -2
    },
    "nap": {
      "label": "",
      "quality": -2
    },
    "snack": {
      "label": "",
      "quality": -2
    },
    "deposiciones": {
      "label": "",
      "quality": -2
    },
    "teacherComments": "Hoy todav\u00eda no han comentado nada"
  },
  {
    "day": 29,
    "month": "4",
    "firstDish": {
      "label": "Macarrones en salsa napolitana casera | Macarrones al ajillo",
      "quality": -2
    },
    "secondDish": {
      "label": "Merluza a la andaluza + ensalada del tiempo ",
      "quality": -2
    },
    "dessertDish": {
      "label": "Pan, yogur",
      "quality": -2
    },
    "nap": {
      "label": "",
      "quality": -2
    },
    "snack": {
      "label": "",
      "quality": -2
    },
    "deposiciones": {
      "label": "",
      "quality": -2
    },
    "teacherComments": "Hoy todav\u00eda no han comentado nada"
  },
  {
    "day": 30,
    "month": "4",
    "firstDish": {
      "label": "Judias verdes a la gallega | Pure de judias verdes",
      "quality": -2
    },
    "secondDish": {
      "label": "Fajitas de pollo + ensalada de tomate ",
      "quality": -2
    },
    "dessertDish": {
      "label": "Pan integral, fruta",
      "quality": -2
    },
    "nap": {
      "label": "",
      "quality": -2
    },
    "snack": {
      "label": "",
      "quality": -2
    },
    "deposiciones": {
      "label": "",
      "quality": -2
    },
    "teacherComments": "Hoy todav\u00eda no han comentado nada"
  }
]