{
    "nombrePlato": null,
    "ingredientesPlato": [
        "PATATA ",
        "ZANAHORIA",
        "PUERRO ",
        "ACEITE DE OLIVA",
        "SAL YODADA"
    ],
    "ingredientesGuarnicion": [],
    "mostrarValoresNutricionales": true,
    "mostrarDetallePlato": true,
    "mostrarIngredientes": true,
    "mostrarAlergenos": true,
    "proteinas": 4,
    "lipidos": 3,
    "hidratos": 28,
    "kcal": 153,
    "grasaSatu": 0,
    "azucares": 8,
    "sal": 1,
    "listaAlergeno": [
        "DI\u00d3XIDO DE AZUFRE Y SULFITOS"
    ]
}